ANSIController/__init__.py
ANSIController/__main__.py
ANSIController/const.py
ANSIController/controls.py
ANSIController/tcolor.py
ANSIController/tparser.py
ANSIController/tprogress.py
ANSIController/tstyles.py
ansicontroller-1.1.2.dist-info/licenses/LICENSE
ansicontroller-1.1.2.dist-info/METADATA
ansicontroller-1.1.2.dist-info/WHEEL
ansicontroller-1.1.2.dist-info/entry_points.txt
ansicontroller-1.1.2.dist-info/top_level.txt
ansicontroller-1.1.2.dist-info/RECORD
