Metadata-Version: 2.4
Name: ANSIController
Version: 1.1.2
Summary: Basic Python Module to control & color & style text in terminal
Home-page: https://github.com/jo0x01/ansicontroller
Author: JoOx01
License: MIT
Keywords: cmd,ansi,terminal,ansi_terminal,ANSIControl,ANSIController,ASNI,ansicontroller,ansi_escape
Classifier: Development Status :: 3 - Alpha
Classifier: Environment :: Console
Classifier: Environment :: Console :: Curses
Classifier: Environment :: Console :: Framebuffer
Classifier: Environment :: Console :: Newt
Classifier: Intended Audience :: Developers
Classifier: Programming Language :: Python :: 3
Classifier: Programming Language :: Python :: 3.4
Classifier: Programming Language :: Python :: 3.5
Classifier: Programming Language :: Python :: 3.6
Classifier: Topic :: Software Development :: Build Tools
Classifier: License :: OSI Approved :: MIT License
Classifier: Operating System :: OS Independent
License-File: LICENSE
Requires-Dist: keyboard
Dynamic: author
Dynamic: classifier
Dynamic: description
Dynamic: description-content-type
Dynamic: home-page
Dynamic: keywords
Dynamic: license
Dynamic: license-file
Dynamic: requires-dist
Dynamic: summary
